hark/__init__.py
hark/cli/__init__.py
hark/cli/hark.py
hark/cli/util.py
hark/client/__init__.py
hark/context/__init__.py
hark/context/imagecache.py
hark/dal/__init__.py
hark/dal/schema.sql
hark/driver/__init__.py
hark/driver/base.py
hark/driver/status.py
hark/driver/virtualbox/__init__.py
hark/exceptions/__init__.py
hark/guest/__init__.py
hark/imagestore/__init__.py
hark/lib/__init__.py
hark/lib/command.py
hark/lib/platform.py
hark/log/__init__.py
hark/models/__init__.py
hark/models/base_image.py
hark/models/folder_share.py
hark/models/image.py
hark/models/machine.py
hark/models/network_interface.py
hark/models/port_mapping.py
hark/networking/__init__.py
hark/procedure/__init__.py
hark/share/__init__.py
hark/share/abstract_share.py
hark/share/nfs.py
hark/ssh/__init__.py
hark/ssh/keys/hark
hark/ssh/keys/hark.pub
hark/util/__init__.py
hark/util/download.py
hark-1.0.0.dev3.data/scripts/hark
hark-1.0.0.dev3.dist-info/DESCRIPTION.rst
hark-1.0.0.dev3.dist-info/METADATA
hark-1.0.0.dev3.dist-info/RECORD
hark-1.0.0.dev3.dist-info/WHEEL
hark-1.0.0.dev3.dist-info/metadata.json
hark-1.0.0.dev3.dist-info/top_level.txt
hark-1.0.0.dev3.dist-info/zip-safe
tests/__init__.py
tests/test_base_image.py
tests/test_cli_hark.py
tests/test_client.py
tests/test_command.py
tests/test_context.py
tests/test_dal.py
tests/test_driver.py
tests/test_guest.py
tests/test_image.py
tests/test_lib_platform.py
tests/test_models.py
tests/test_networking.py
tests/test_ssh.py
tests/test_util.py
